usim800-hamilkar/Communicate.py
usim800-hamilkar/__init__.py
usim800-hamilkar/usim800.py
usim800-hamilkar/Info/__init__.py
usim800-hamilkar/Info/info.py
usim800-hamilkar/Parser/ATParser.py
usim800-hamilkar/Parser/JsonParser.py
usim800-hamilkar/Parser/__init__.py
usim800-hamilkar/Parser/stack.py
usim800-hamilkar/Parser/test.py
usim800-hamilkar/Request/Request.py
usim800-hamilkar/Request/__init__.py
usim800-hamilkar/Sms/__init__.py
usim800-hamilkar/Sms/sms.py
usim800_hamilkar/Communicate.py
usim800_hamilkar/__init__.py
usim800_hamilkar/usim800.py
usim800_hamilkar/usim800_hamilkar.py
usim800_hamilkar/Info/__init__.py
usim800_hamilkar/Info/info.py
usim800_hamilkar/Parser/ATParser.py
usim800_hamilkar/Parser/JsonParser.py
usim800_hamilkar/Parser/__init__.py
usim800_hamilkar/Parser/stack.py
usim800_hamilkar/Parser/test.py
usim800_hamilkar/Request/Request.py
usim800_hamilkar/Request/__init__.py
usim800_hamilkar/Sms/__init__.py
usim800_hamilkar/Sms/sms.py
usim800_hamilkar-0.0.3.dist-info/LICENSE
usim800_hamilkar-0.0.3.dist-info/METADATA
usim800_hamilkar-0.0.3.dist-info/WHEEL
usim800_hamilkar-0.0.3.dist-info/top_level.txt
usim800_hamilkar-0.0.3.dist-info/RECORD
